monocle_mcp/mcp_server.py
monocle_mcp-0.7.2.dist-info/METADATA
monocle_mcp-0.7.2.dist-info/WHEEL
monocle_mcp-0.7.2.dist-info/entry_points.txt
monocle_mcp-0.7.2.dist-info/licenses/LICENSE
monocle_mcp-0.7.2.dist-info/RECORD
