Metadata-Version: 2.4
Name: monocle_mcp
Version: 0.7.2
Summary: Monocle MCP server: prompts and tools for enabling and analyzing Monocle tracing in GenAI apps.
Author-email: "Okahu Inc." <okahu-pypi@okahu.ai>
License: Apache-2.0
License-File: LICENSE
Classifier: Intended Audience :: Developers
Classifier: License :: OSI Approved :: Apache Software License
Classifier: Operating System :: OS Independent
Classifier: Programming Language :: Python :: 3
Classifier: Topic :: Software Development :: Libraries :: Application Frameworks
Classifier: Topic :: Software Development :: Libraries :: Python Modules
Requires-Python: >=3.8
Requires-Dist: click>=8.0.0
Requires-Dist: mcp>=1.12.1
Requires-Dist: monocle-apptrace>=0.5.0
